calcipy/__init__.py
calcipy/_runtime_type_check_setup.py
calcipy/can_skip.py
calcipy/cli.py
calcipy/code_tag_collector/__init__.py
calcipy/code_tag_collector/_collector.py
calcipy/collection.py
calcipy/dot_dict/__init__.py
calcipy/dot_dict/_dot_dict.py
calcipy/experiments/__init__.py
calcipy/experiments/bump_programmatically.py
calcipy/experiments/check_duplicate_test_names.py
calcipy/experiments/sync_package_dependencies.py
calcipy/file_search.py
calcipy/invoke_helpers.py
calcipy/markdown_table.py
calcipy/md_writer/__init__.py
calcipy/md_writer/_writer.py
calcipy/noxfile/__init__.py
calcipy/noxfile/_noxfile.py
calcipy/py.typed
calcipy/scripts.py
calcipy/tasks/__init__.py
calcipy/tasks/all_tasks.py
calcipy/tasks/cl.py
calcipy/tasks/defaults.py
calcipy/tasks/doc.py
calcipy/tasks/executable_utils.py
calcipy/tasks/lint.py
calcipy/tasks/most_tasks.py
calcipy/tasks/nox.py
calcipy/tasks/pack.py
calcipy/tasks/tags.py
calcipy/tasks/test.py
calcipy/tasks/types.py
calcipy-5.0.0.dist-info/LICENSE
calcipy-5.0.0.dist-info/METADATA
calcipy-5.0.0.dist-info/WHEEL
calcipy-5.0.0.dist-info/entry_points.txt
calcipy-5.0.0.dist-info/RECORD
