Metadata-Version: 2.1
Name: calcipy
Version: 5.0.0
Summary: Python package to simplify development
Home-page: https://github.com/kyleking/calcipy
License: MIT
Keywords: calcipy_template
Author: Kyle King
Author-email: dev.act.kyle@gmail.com
Requires-Python: >=3.9.13,<4.0.0
Classifier: Development Status :: 4 - Beta
Classifier: Framework :: Pytest
Classifier: Intended Audience :: Developers
Classifier: License :: OSI Approved :: MIT License
Classifier: Operating System :: OS Independent
Classifier: Programming Language :: Python :: 3
Classifier: Programming Language :: Python :: 3.10
Classifier: Programming Language :: Python :: 3.11
Classifier: Programming Language :: Python :: 3.12
Classifier: Programming Language :: Python :: 3.13
Classifier: Programming Language :: Python :: 3.9
Classifier: Topic :: Software Development :: Libraries
Classifier: Topic :: Utilities
Provides-Extra: ddict
Provides-Extra: doc
Provides-Extra: experimental
Provides-Extra: lint
Provides-Extra: nox
Provides-Extra: tags
Provides-Extra: test
Provides-Extra: types
Requires-Dist: arrow (>=1.3.0) ; extra == "tags"
Requires-Dist: beartype (>=0.19.0)
Requires-Dist: commitizen (>=3.29.1) ; extra == "doc"
Requires-Dist: corallium (>=2.0.1)
Requires-Dist: griffe (>=1.3.2) ; extra == "experimental"
Requires-Dist: invoke (>=2.2.0)
Requires-Dist: mkdocs (>=1.6.1) ; extra == "doc"
Requires-Dist: mkdocs-gen-files (>=0.5.0) ; extra == "doc"
Requires-Dist: mkdocs-material (>=9.5.39) ; extra == "doc"
Requires-Dist: mkdocstrings[python] (>=0.26.1) ; extra == "doc"
Requires-Dist: mypy (>=1.11.2) ; extra == "types"
Requires-Dist: nox-poetry (>=1.0.3) ; extra == "nox"
Requires-Dist: pymdown-extensions (>=10.11.2) ; extra == "doc"
Requires-Dist: pytest (>=8.3.3) ; extra == "test"
Requires-Dist: pytest-cov (>=5.0.0) ; extra == "test"
Requires-Dist: pytest-randomly (>=3.15.0) ; extra == "test"
Requires-Dist: pytest-watcher (>=0.4.3) ; extra == "test"
Requires-Dist: python-box (>=7.2.0) ; extra == "ddict"
Requires-Dist: pyyaml (>=6.0.2) ; extra == "tags"
Requires-Dist: ruff (>=0.6.9) ; extra == "lint"
Requires-Dist: semver (>=3.0.2) ; extra == "experimental"
Requires-Dist: virtualenv (>=20.26.6) ; extra == "nox"
Project-URL: Bug Tracker, https://github.com/kyleking/calcipy/issues
Project-URL: Changelog, https://github.com/kyleking/calcipy/blob/main/docs/docs/CHANGELOG.md
Project-URL: Documentation, https://calcipy.kyleking.me
Project-URL: Repository, https://github.com/kyleking/calcipy
